{"P5": {"labels": ["\u6587\u5b66", "\u8bd7\u96c6"], "postTitle": "\u300a\u5b66\u5802\u6811\u300b", "postUrl": "post/%E3%80%8A-xue-tang-shu-%E3%80%8B.html", "createdDate": "2025-11-02", "dateLabelColor": "#0969da"}, "P4": {"labels": ["\u6587\u5b66", "\u6742\u6587"], "postTitle": "\u4e16\u8bf4\u65b0\u7f16", "postUrl": "post/shi-shuo-xin-bian.html", "createdDate": "2025-10-31", "dateLabelColor": "#0969da"}, "labelColorDict": {"about": "#f380f1", "link": "#65fcb8", "\u6587\u5b66": "#F71E1E", "\u6742\u6587": "#f5ace8", "\u7b14\u8bb0": "#980fb5", "\u8bd7\u96c6": "#20D432"}}